[
  {
    "name": "Delhi",
    "temp": 30,
    "rain": false
  },
  {
    "name": "Mumbai",
    "temp": 32,
    "rain": true
  },
  {
    "name": "Chennai",
    "temp": 35,
    "rain": false
  },
  {
    "name": "Bangalore",
    "temp": 25,
    "rain": true
  },
  {
    "name": "Kolkata",
    "temp": 31,
    "rain": false
  },
  {
    "name": "Hyderabad",
    "temp": 33,
    "rain": true
  },
  {
    "name": "Pune",
    "temp": 29,
    "rain": false
  },
  {
    "name": "Ahmedabad",
    "temp": 34,
    "rain": true
  },
  {
    "name": "Surat",
    "temp": 31,
    "rain": false
  },
  {
    "name": "Jaipur",
    "temp": 27,
    "rain": true
  },
  {
    "name": "Lucknow",
    "temp": 30,
    "rain": false
  },
  {
    "name": "Kanpur",
    "temp": 29,
    "rain": true
  },
  {
    "name": "Nagpur",
    "temp": 34,
    "rain": false
  },
  {
    "name": "Visakhapatnam",
    "temp": 32,
    "rain": true
  },
  {
    "name": "Bhopal",
    "temp": 30,
    "rain": false
  },
  {
    "name": "Patna",
    "temp": 31,
    "rain": true
  },
  {
    "name": "Vadodara",
    "temp": 30,
    "rain": false
  },
  {
    "name": "Ghaziabad",
    "temp": 28,
    "rain": true
  },
  {
    "name": "Ludhiana",
    "temp": 27,
    "rain": false
  },
  {
    "name": "Udupi",
    "temp": 32,
    "rain": false
  }
]